{
  "plants": [
    // ======== الحبوب (20 صنف) ========
    {
      "id": "cereal-1",
      "type": { "ar": "الحبوب", "fr": "Céréales", "en": "Cereals" },
      "name": { "ar": "قمح صلب - مغربية 117", "fr": "Blé dur Marocaine 117", "en": "Durum Wheat Marocaine 117" },
      "scientific_name": "Triticum durum",
      "origin": { "ar": "مستنبط في المغرب، منتشر في الجزائر", "fr": "Sélectionné au Maroc, répandu en Algérie" },
      "growing_regions": ["سطيف", "تيارت", "معسكر"],
      "yield": "45-60 قنطار/هـ",
      "diseases": [
        {
          "name": { "ar": "صدأ الساق الأسود", "fr": "Rouille noire" },
          "treatment": {
            "pesticide": { "ar": "توباز 100 EC", "fr": "Topaz 100 EC" },
            "dosage": "0.5 لتر/هـ"
          }
        }
      ],
      "fertilizers": [
        {
          "stage": { "ar": "الإنبات", "fr": "Germination" },
          "N": "20 كغ/هـ",
          "P": "30 كغ/هـ"
        },
        {
          "stage": { "ar": "الطور الخضري", "fr": "Croissance végétative" },
          "N": "40 كغ/هـ",
          "K": "20 كغ/هـ"
        }
      ]
    },
    {
      "id": "cereal-2",
      "type": { "ar": "الحبوب", "fr": "Céréales", "en": "Cereals" },
      "name": { "ar": "شعير - صهيب", "fr": "Orge Saheb", "en": "Barley Saheb" },
      "scientific_name": "Hordeum vulgare",
      "origin": { "ar": "مستنبط محلياً بوهران", "fr": "Sélection locale à Oran" },
      "drought_tolerance": "عالي",
      "pesticides": [
        {
          "active_ingredient": { "ar": "ترياديمينون", "fr": "Triadiménol" },
          "dosage": "0.8 لتر/هـ",
          "safety_period": { "ar": "21 يوم", "fr": "21 jours" }
        }
      ]
    },
    // ... (18 أصناف حبوب إضافية)
    
    // ======== الخضروات (60 صنف) ========
    {
      "id": "vegetable-1",
      "type": { "ar": "الخضروات", "fr": "Légumes", "en": "Vegetables" },
      "name": { "ar": "طماطم - ريوجين", "fr": "Tomate Rio Grande", "en": "Rio Grande Tomato" },
      "scientific_name": "Solanum lycopersicum",
      "algerian_variety": true,
      "developed_by": { "ar": "معهد سطيف الزراعي", "fr": "Institut Agricole de Sétif" },
      "fruit_weight": "80-100 غ",
      "resistance": ["الذبول الفيوزاريومي", "فيروس تبرقش الطماطم"],
      "fertilizers": [
        {
          "stage": { "ar": "ما بعد الزرع", "fr": "Post-plantation" },
          "N": "30 كغ/هـ",
          "P": "40 كغ/هـ",
          "K": "20 كغ/هـ"
        }
      ]
    },
    {
      "id": "vegetable-2",
      "type": { "ar": "الخضروات", "fr": "Légumes", "en": "Vegetables" },
      "name": { "ar": "فلفل حار - قالمي", "fr": "Piment de Guelma", "en": "Guelma Chili" },
      "scientific_name": "Capsicum annuum",
      "scoville_units": "30,000-50,000",
      "traditional_uses": ["الحريرة", "الصلصة الحارة"],
      "pesticides": [
        {
          "active_ingredient": { "ar": "إيميداكلوبريد", "fr": "Imidaclopride" },
          "algerian_approved": true,
          "dosage": "0.3 لتر/هـ"
        }
      ]
    },
    // ... (58 أصناف خضروات إضافية)
    
    // ======== الأشجار المثمرة (20 صنف) ========
    {
      "id": "tree-1",
      "type": { "ar": "الأشجار المثمرة", "fr": "Arbres fruitiers", "en": "Fruit Trees" },
      "name": { "ar": "زيتون - شملالي", "fr": "Olive Chemlal", "en": "Chemlal Olive" },
      "scientific_name": "Olea europaea",
      "origin": { "ar": "منطقة القبائل", "fr": "Kabylie" },
      "oil_yield": "18-22%",
      "harvest_period": { "ar": "نوفمبر-يناير", "fr": "Novembre-Janvier" },
      "fertilizers": [
        {
          "stage": { "ar": "ما بعد القطاف", "fr": "Post-récolte" },
          "P": "40 كغ/هـ",
          "K": "30 كغ/هـ"
        }
      ]
    },
    {
      "id": "tree-2",
      "type": { "ar": "الأشجار المثمرة", "fr": "Arbres fruitiers", "en": "Fruit Trees" },
      "name": { "ar": "نخيل - دقلة نور", "fr": "Palmier dattier Deglet Nour", "en": "Deglet Nour Date Palm" },
      "scientific_name": "Phoenix dactylifera",
      "growing_areas": ["بسكرة", "وادي سوف", "تقرت"],
      "water_requirements": "20,000 م³/هـ/سنة",
      "production": "80-120 كغ/نخلة",
      "diseases": [
        {
          "name": { "ar": "دودة البلح", "fr": "Ver du palmier" },
          "treatment": {
            "pesticide": { "ar": "كلوربيريفوس", "fr": "Chlorpyrifos" },
            "dosage": "1.5 لتر/هـ"
          }
        }
      ]
    },
    // ... (18 أصناف أشجار إضافية)
  ],

  "agricultural_zones": {
    "north": {
      "description": { 
        "ar": "المنطقة الشمالية (مناخ متوسطي)",
        "fr": "Région nord (climat méditerranéen)"
      },
      "soil_types": ["تربة طينية", "تربة حمراء"],
      "major_crops": ["الحبوب", "الكرمة", "الحمضيات"]
    },
    "high_plateaus": {
      "description": { 
        "ar": "الهضاب العليا (مناخ شبه جاف)",
        "fr": "Hauts plateaux (climat semi-aride)"
      },
      "soil_types": ["تربة حمراء", "تربة جبسية"],
      "major_crops": ["الحبوب", "الزراعات العلفية"]
    },
    "south": {
      "description": { 
        "ar": "المنطقة الجنوبية (مناخ صحراوي)",
        "fr": "Région sud (climat désertique)"
      },
      "soil_types": ["تربة رملية", "تربة ملحية"],
      "major_crops": ["النخيل", "الخضروات المبكرة"]
    }
  },

  "research_sources": [
    {
      "institute": { 
        "ar": "المعهد الوطني للبحث الزراعي (INRAA)", 
        "fr": "Institut National de la Recherche Agronomique d'Algérie" 
      },
      "location": "الجزائر العاصمة",
      "specialties": ["تربية النبات", "وقاية المزروعات", "الموارد المائية"]
    },
    {
      "institute": { 
        "ar": "المركز الوطني للبحوث الزراعية (CRSTRA)", 
        "fr": "Centre de Recherche Scientifique et Technique sur les Régions Arides" 
      },
      "location": "بسكرة",
      "specialties": ["زراعة الواحات", "النخيل", "التكيف مع الجفاف"]
    }
  ]
}
